ictasks/__init__.py
ictasks/config.py
ictasks/main_cli.py
ictasks/py.typed
ictasks/session.py
ictasks/stopping_condition.py
ictasks/task.py
ictasks/worker.py
ictasks/scheduler/__init__.py
ictasks/scheduler/main.py
ictasks/scheduler/scheduler.py
ictasks/scheduler/db/__init__.py
ictasks/scheduler/db/db_interface.py
ictasks/scheduler/models/__init__.py
ictasks/scheduler/models/fields.py
ictasks/scheduler/models/model.py
ictasks/scheduler/models/queue.py
ictasks/scheduler/models/resource.py
ictasks/scheduler/models/task.py
ictasks/scheduler/models/user.py
ictasks/scheduler/schedulers/__init__.py
ictasks/scheduler/schedulers/slurm.py
ictasks/scheduler/schedulers/slurm_parser.py
ictasks/scheduler/schedulers/slurm_rest.py
ictasks-0.2.4.dist-info/licenses/LICENSE.txt
ictasks-0.2.4.dist-info/METADATA
ictasks-0.2.4.dist-info/WHEEL
ictasks-0.2.4.dist-info/entry_points.txt
ictasks-0.2.4.dist-info/top_level.txt
ictasks-0.2.4.dist-info/RECORD
