Metadata-Version: 2.4
Name: ictasks
Version: 0.2.4
Summary: A utility to run multiple small tasks in a single HPC job submission.
Author-email: "James Grogan, Irish Centre for High End Computing" <james.grogan@ichec.ie>
Project-URL: Repository, https://git.ichec.ie/performance/toolshed/ictasks
Project-URL: Homepage, https://git.ichec.ie/performance/toolshed/ictasks
Keywords: Slurm,HPC,tasks,MPI
Classifier: Development Status :: 3 - Alpha
Classifier: Programming Language :: Python :: 3
Classifier: License :: OSI Approved :: GNU General Public License v3 or later (GPLv3+)
Classifier: Operating System :: OS Independent
Classifier: Topic :: System :: Distributed Computing
Requires-Python: >=3.10
License-File: LICENSE.txt
Requires-Dist: icsystemutils==0.2.5
Provides-Extra: test
Requires-Dist: pytest; extra == "test"
Requires-Dist: pytest-cov; extra == "test"
Requires-Dist: pytest-sugar; extra == "test"
Requires-Dist: black; extra == "test"
Requires-Dist: mypy; extra == "test"
Requires-Dist: pylint; extra == "test"
Requires-Dist: flake8; extra == "test"
Requires-Dist: numba==0.61.2; extra == "test"
Dynamic: license-file
